[
  {
    "name": "Volkswagen",
    "type": "PASSENGER",
    "models": [
      {
        "name": "Golf",
        "generations": [
          {
            "name": "Mk4",
            "period": "1997–2003",
            "bodyStyles": ["Hatchback", "Wagon", "Cabriolet"],
            "engines": [
              {
                "engineType": "Petrol",
                "engineCapacity_cm3": 1390,
                "enginePower_kW": 55,
                "enginePower_HP": 75,
                "engineCodes": ["AKQ", "APE"],
                "description": "1.4 MPI"
              },
              {
                "engineType": "Petrol",
                "engineCapacity_cm3": 1595,
                "enginePower_kW": 74,
                "enginePower_HP": 100,
                "engineCodes": ["AEH", "AKL", "BFQ", "BSE"],
                "description": "1.6 MPI"
              },
              {
                "engineType": "Petrol",
                "engineCapacity_cm3": 1781,
                "enginePower_kW": 92,
                "enginePower_HP": 125,
                "engineCodes": ["AGN", "AUM"],
                "description": "1.8 20V"
              },
              {
                "engineType": "Petrol",
                "engineCapacity_cm3": 1781,
                "enginePower_kW": 110,
                "enginePower_HP": 150,
                "engineCodes": ["AGU", "ARZ", "AUQ"],
                "description": "1.8T 20V Turbo"
              },
              {
                "engineType": "Petrol",
                "engineCapacity_cm3": 1984,
                "enginePower_kW": 85,
                "enginePower_HP": 115,
                "engineCodes": ["AQY", "AZJ"],
                "description": "2.0 MPI"
              },
              {
                "engineType": "Petrol",
                "engineCapacity_cm3": 2324,
                "enginePower_kW": 110,
                "enginePower_HP": 150,
                "engineCodes": ["AGZ"],
                "description": "2.3 VR5 10V"
              },
              {
                "engineType": "Petrol",
                "engineCapacity_cm3": 2324,
                "enginePower_kW": 125,
                "enginePower_HP": 170,
                "engineCodes": ["AQN"],
                "description": "2.3 VR5 20V"
              },
              {
                "engineType": "Petrol",
                "engineCapacity_cm3": 3189,
                "enginePower_kW": 184,
                "enginePower_HP": 250,
                "engineCodes": ["BFH"],
                "description": "3.2 VR6 (R32)"
              },
              {
                "engineType": "Diesel",
                "engineCapacity_cm3": 1896,
                "enginePower_kW": 50,
                "enginePower_HP": 70,
                "engineCodes": ["AEY", "AGP"],
                "description": "1.9 SDI"
              },
              {
                "engineType": "Diesel",
                "engineCapacity_cm3": 1896,
                "enginePower_kW": 66,
                "enginePower_HP": 90,
                "engineCodes": ["ALH", "AHF", "ASV"],
                "description": "1.9 TDI"
              },
              {
                "engineType": "Diesel",
                "engineCapacity_cm3": 1896,
                "enginePower_kW": [85, 96, 110],
                "enginePower_HP": [115, 130, 150],
                "engineCodes": ["AJM", "ASZ", "ARL"],
                "description": "1.9 TDI PD"
              }
            ]
          }
        ]
      },
      {
        "name": "Bora",
        "generations": [
          {
            "name": "Mk4 (1J)",
            "period": "1999–2005",
            "bodyStyles": ["Sedan", "Wagon"],
            "engines": []
          }
        ]
      },
      {
        "name": "New Beetle",
        "generations": [
          {
            "name": "Type 9C",
            "period": "1997–2011",
            "bodyStyles": ["Hatchback", "Convertible"],
            "engines": []
          }
        ]
      }
    ]
  },
  {
    "name": "Audi",
    "type": "PASSENGER",
    "models": [
      {
        "name": "A3",
        "generations": [
          {
            "name": "Mk1 (8L)",
            "period": "1996–2003",
            "bodyStyles": ["Hatchback (3-door)", "Hatchback (5-door)"],
            "engines": []
          }
        ]
      },
      {
        "name": "TT",
        "generations": [
          {
            "name": "Mk1 (8N)",
            "period": "1998–2006",
            "bodyStyles": ["Coupé", "Roadster"],
            "engines": []
          }
        ]
      }
    ]
  },
  {
    "name": "SEAT",
    "type": "PASSENGER",
    "models": [
      {
        "name": "León",
        "generations": [
          {
            "name": "Mk1 (1M)",
            "period": "1999–2006",
            "bodyStyles": ["Hatchback"],
            "engines": []
          }
        ]
      },
      {
        "name": "Toledo",
        "generations": [
          {
            "name": "Mk2 (1M)",
            "period": "1998–2004",
            "bodyStyles": ["Sedan"],
            "engines": []
          }
        ]
      }
    ]
  },
  {
    "name": "Škoda",
    "type": "PASSENGER",
    "models": [
      {
        "name": "Octavia",
        "generations": [
          {
            "name": "Mk1 (1U)",
            "period": "1996–2004",
            "bodyStyles": ["Liftback", "Wagon"],
            "engines": []
          }
        ]
      }
    ]
  }
]